.gitignore
LICENSE
MANIFEST.in
README.md
setup.py
docs/rainier_vmap_sm.jpg
vmap/__init__.py
vmap/all_vmap.py
vmap/disp2v.py
vmap/disp_view.sh
vmap/dummy.tsai
vmap/golive_proc.py
vmap/post_vmap.sh
vmap/seasonal_mos.py
vmap/vmap.py
vmap/wv_cdate.py
vmap.egg-info/PKG-INFO
vmap.egg-info/SOURCES.txt
vmap.egg-info/dependency_links.txt
vmap.egg-info/requires.txt
vmap.egg-info/top_level.txt