Metadata-Version: 2.1
Name: vmap
Version: 1.1.1
Summary: Velocity map generation using the Ames Stereo Pipeline image correlator
Home-page: https://github.com/dshean/vmap
Author: David Shean
Author-email: dshean@gmail.com
License: MIT
License-File: LICENSE
Requires-Dist: numpy
Requires-Dist: gdal
Requires-Dist: pygeotools
Requires-Dist: demcoreg
